webcolors-stubs/__init__.pyi
webcolors-stubs/py.typed
webcolors_stubs-0.0.3.dist-info/LICENSE
webcolors_stubs-0.0.3.dist-info/METADATA
webcolors_stubs-0.0.3.dist-info/WHEEL
webcolors_stubs-0.0.3.dist-info/entry_points.txt
webcolors_stubs-0.0.3.dist-info/top_level.txt
webcolors_stubs-0.0.3.dist-info/RECORD
