Metadata-Version: 2.1
Name: webcolors-stubs
Version: 0.0.3
Summary: PEP 561 based Type information for webcolors.
Home-page: https://github.com/domdfcoding/webcolors-stubs
Author: Dominic Davis-Foster
Author-email: dominic@davis-foster.co.uk
License: BSD License
Project-URL: Documentation, https://webcolors-stubs.readthedocs.io
Project-URL: Issue Tracker, https://github.com/domdfcoding/webcolors-stubs/issues
Project-URL: Source Code, https://github.com/domdfcoding/webcolors-stubs
Keywords: webcolors css type-stubs
Platform: UNKNOWN
Classifier: Development Status :: 4 - Beta
Classifier: Intended Audience :: Developers
Classifier: Operating System :: OS Independent
Classifier: Topic :: Utilities
Classifier: Environment :: Web Environment
Classifier: Programming Language :: Python :: 3.6
Classifier: Programming Language :: Python :: Implementation :: CPython
Classifier: Programming Language :: Python :: 3.7
Classifier: Programming Language :: Python :: 3.8
Classifier: Programming Language :: Python :: 3.9
Classifier: Programming Language :: Python :: Implementation :: PyPy
Classifier: Programming Language :: Python
Classifier: Programming Language :: Python :: 3 :: Only
Classifier: License :: OSI Approved :: BSD License
Requires-Python: >=3.6
Requires-Dist: webcolors
Provides-Extra: all
